ncbiutils/__init__.py
ncbiutils/http.py
ncbiutils/ncbiutils.py
ncbiutils/pmcxmlparser.py
ncbiutils/pubmed.py
ncbiutils/pubmedxmlparser.py
ncbiutils/types.py
ncbiutils/xml.py
ncbiutils-0.7.1.dist-info/LICENSE
ncbiutils-0.7.1.dist-info/WHEEL
ncbiutils-0.7.1.dist-info/METADATA
ncbiutils-0.7.1.dist-info/RECORD
