Metadata-Version: 2.1
Name: ncbiutils
Version: 0.7.1
Summary: Retrieve article records from NCBI via E-utilities
Home-page: https://github.com/PathwayCommons/ncbiutils
License: MIT
Author: Biofactoid
Author-email: support@biofactoid.org
Maintainer: Biofactoid
Maintainer-email: support@biofactoid.org
Requires-Python: >=3.8,<4.0
Classifier: Environment :: Console
Classifier: Intended Audience :: Science/Research
Classifier: License :: OSI Approved :: MIT License
Classifier: License :: OSI Approved :: MIT No Attribution License (MIT-0)
Classifier: Operating System :: OS Independent
Classifier: Programming Language :: Python :: 3
Classifier: Programming Language :: Python :: 3.8
Classifier: Programming Language :: Python :: 3.9
Classifier: Programming Language :: Python :: 3.10
Classifier: Programming Language :: Python :: 3.11
Classifier: Programming Language :: Python :: 3.8
Classifier: Programming Language :: Python :: 3.9
Classifier: Topic :: Scientific/Engineering :: Artificial Intelligence
Requires-Dist: loguru (>=0.6.0,<0.7.0)
Requires-Dist: lxml (>=4.8.0,<5.0.0)
Requires-Dist: pydantic (>=1.9.0,<2.0.0)
Requires-Dist: requests (>=2.27.1,<3.0.0)
Project-URL: Repository, https://github.com/PathwayCommons/ncbiutils
